{
  "defaultLanguage": "en-AU",
  "initialSequence": "92fab14f-7de5-4473-b6ab-c972dfa8096b",
  "supportedLanguages": [
    "en-AU"
  ],
  "description": "Used for Testing Only",
  "name": "OzInboundIVR",
  "uiMetaData": {
    "bridgeServerActions": [
      {
        "category": "salesforcePOC",
        "deprecated": false,
        "description": "Get Contact By Phone Number",
        "name": "GetContactByPhoneNumber",
        "published": true,
        "tags": [],
        "id": "GetContactByPhoneNumber",
        "requests": [
          {
            "format": "rest",
            "inputSchema": {
              "title": "PhoneNumberRequest",
              "description": "A phone number based request",
              "required": [
                "PhoneNumber"
              ],
              "type": "object",
              "properties": {
                "PhoneNumber": {
                  "type": "string",
                  "description": "The phone number used to query the CRM",
                  "name": "PhoneNumber",
                  "required": true
                },
                "CustomAttribute": {
                  "type": "string",
                  "description": "Additional attribute requested",
                  "name": "CustomAttribute"
                }
              }
            },
            "method": "POST",
            "successSchema": {
              "title": "Contact",
              "description": "A Contact",
              "type": "object",
              "required": [
                "Contact"
              ],
              "properties": {
                "Contact.Address.City": {
                  "type": "string",
                  "description": "City of the Address",
                  "name": "Contact.Address.City",
                  "required": false
                },
                "Contact.Address.Country": {
                  "type": "string",
                  "description": "Country of the Address",
                  "name": "Contact.Address.Country",
                  "required": false
                },
                "Contact.Address.Line1": {
                  "type": "string",
                  "description": "Line 1 of the Address",
                  "name": "Contact.Address.Line1",
                  "required": false
                },
                "Contact.Address.Line2": {
                  "type": "string",
                  "description": "Line 2 of the Address",
                  "name": "Contact.Address.Line2",
                  "required": false
                },
                "Contact.Address.Line3": {
                  "type": "string",
                  "description": "Line 3 of the Address",
                  "name": "Contact.Address.Line3",
                  "required": false
                },
                "Contact.Address.PostalCode": {
                  "type": "string",
                  "description": "Postal Code of the Address",
                  "name": "Contact.Address.PostalCode",
                  "required": false
                },
                "Contact.Address.State": {
                  "type": "string",
                  "description": "State of the Address",
                  "name": "Contact.Address.State",
                  "required": false
                },
                "Contact.Address.Type": {
                  "type": "integer",
                  "description": "Type of Address",
                  "name": "Contact.Address.Type",
                  "required": false
                },
                "Contact.EmailAddresses.EmailAddress.EmailAddress": {
                  "type": "array",
                  "description": "Array of Email Addresses of the Contact",
                  "items": {
                    "type": "string",
                    "description": "Email Address of the Contact"
                  },
                  "name": "Contact.EmailAddresses.EmailAddress.EmailAddress",
                  "required": false
                },
                "Contact.EmailAddresses.EmailAddress.EmailType": {
                  "type": "array",
                  "description": "Array of Email Addresses of the Contact",
                  "items": {
                    "type": "integer",
                    "description": "Type of Email Address"
                  },
                  "name": "Contact.EmailAddresses.EmailAddress.EmailType",
                  "required": false
                },
                "Contact.FullName": {
                  "type": "string",
                  "description": "Full Name of the Contact",
                  "name": "Contact.FullName",
                  "required": false
                },
                "Contact.FirstName": {
                  "type": "string",
                  "description": "First Name of the Contact",
                  "name": "Contact.FirstName",
                  "required": false
                },
                "Contact.Id": {
                  "type": "string",
                  "description": "ID of the Contact",
                  "name": "Contact.Id",
                  "required": false
                },
                "Contact.LastName": {
                  "type": "string",
                  "description": "Last Name of the Contact",
                  "name": "Contact.LastName",
                  "required": false
                },
                "Contact.PhoneNumbers.PhoneNumber.Number": {
                  "type": "array",
                  "description": "Array of Phone Numbers of the Contact",
                  "items": {
                    "type": "string",
                    "description": "Phone Number of the Contact"
                  },
                  "name": "Contact.PhoneNumbers.PhoneNumber.Number",
                  "required": false
                },
                "Contact.PhoneNumbers.PhoneNumber.PhoneType": {
                  "type": "array",
                  "description": "Array of Phone Numbers of the Contact",
                  "items": {
                    "type": "integer",
                    "description": "Type of Phone Number"
                  },
                  "name": "Contact.PhoneNumbers.PhoneNumber.PhoneType",
                  "required": false
                },
                "Contact.CustomAttribute": {
                  "type": "string",
                  "description": "The value of the custom attribute provided in the request",
                  "name": "Contact.CustomAttribute",
                  "required": false
                }
              }
            }
          }
        ]
      }
    ],
    "screenPops": [],
    "voiceXmlOperations": [],
    "contactList": [],
    "scripts": [
      {
        "id": "58a574a0-a4ab-11e6-b25e-4f1c124e1cea",
        "name": "BaseQ",
        "variables": {
          "description": "The custom variables for this script",
          "title": "Variables",
          "type": "object",
          "properties": {}
        }
      }
    ]
  },
  "nextTrackingNumber": 97,
  "type": "inboundcall",
  "manifest": {
    "queue": [
      {
        "name": "OzInbound_Q",
        "id": "3c61d082-33b9-41e4-9d5e-b4def04448b0",
        "context": [
          {
            "name": "Transfer to ACD",
            "actionName": "Transfer to ACD",
            "id": "8d3e7142-7410-41a8-be87-526dcb35fac4"
          },
          {
            "name": "Transfer to ACD",
            "actionName": "Transfer to ACD",
            "id": "50de39c4-a32a-472d-84b0-e0d312a43662"
          }
        ]
      }
    ],
    "bridgeAction": [
      {
        "name": "GetContactByPhoneNumber",
        "id": "GetContactByPhoneNumber",
        "context": [
          {
            "name": "Salesforce Data Dip",
            "actionName": "Call Bridge Action",
            "id": "e24bc584-8441-4e66-96ee-3fcd3cbc95eb"
          }
        ]
      }
    ],
    "composerScript": [
      {
        "name": "BaseQ",
        "id": "58a574a0-a4ab-11e6-b25e-4f1c124e1cea",
        "context": [
          {
            "name": "Agent Script",
            "actionName": "Set Screen Pop",
            "id": "01df0827-4395-458b-8a07-10351771a8ed"
          }
        ]
      }
    ],
    "language": [
      {
        "id": "en-AU"
      }
    ],
    "userPrompt": [
      {
        "name": "AUGenericWelcome",
        "id": "bfc3f9b6-8b2b-45ee-8652-0a939e617753",
        "context": [
          {
            "id": "19df021e-9925-445e-a130-dfe1337de554"
          }
        ]
      }
    ],
    "systemPrompt": []
  },
  "isSecure": false,
  "debugSettings": {},
  "defaultSettings": {
    "CollectInputAction": {
      "interDigitTimeout": {
        "config": {
          "lit": {
            "pos": 1,
            "text": "P0D0H0M3S0F",
            "type": "dur"
          }
        },
        "text": "P0D0H0M3S0F",
        "type": "dur",
        "uiMetaData": {
          "mode": 1
        },
        "metaData": {}
      },
      "noEntryTimeout": {
        "config": {
          "lit": {
            "pos": 1,
            "text": "P0D0H0M5S0F",
            "type": "dur"
          }
        },
        "text": "P0D0H0M5S0F",
        "type": "dur",
        "uiMetaData": {
          "mode": 1
        },
        "metaData": {}
      }
    },
    "DialExtensionAction": {
      "digitTimeout": {
        "config": {
          "lit": {
            "pos": 1,
            "text": "P0D0H0M6S0F",
            "type": "dur"
          }
        },
        "text": "P0D0H0M6S0F",
        "type": "dur",
        "uiMetaData": {
          "mode": 1
        },
        "metaData": {}
      }
    },
    "SpeechRec": {
      "speechRecMinConfidence": {
        "config": {
          "lit": {
            "pos": 1,
            "text": "50",
            "type": "int"
          }
        },
        "text": "50",
        "type": "int",
        "uiMetaData": {
          "mode": 1
        },
        "metaData": {}
      },
      "speechRecTimeoutComplete": {
        "config": {
          "lit": {
            "pos": 1,
            "text": "P0D0H0M0S500F",
            "type": "dur"
          }
        },
        "text": "P0D0H0M0S500F",
        "type": "dur",
        "uiMetaData": {
          "mode": 1
        },
        "metaData": {}
      },
      "speechRecTimeoutIncomplete": {
        "config": {
          "lit": {
            "pos": 1,
            "text": "P0D0H0M1S500F",
            "type": "dur"
          }
        },
        "text": "P0D0H0M1S500F",
        "type": "dur",
        "uiMetaData": {
          "mode": 1
        },
        "metaData": {}
      },
      "speechRecTimeoutTotal": {
        "config": {
          "lit": {
            "pos": 1,
            "text": "P0D0H0M20S0F",
            "type": "dur"
          }
        },
        "text": "P0D0H0M20S0F",
        "type": "dur",
        "uiMetaData": {
          "mode": 1
        },
        "metaData": {}
      },
      "invalidSpeechRecPromptsList": [
        {
          "defaultAudio": {
            "config": {
              "ToAudio": {
                "pos": 1,
                "text": "ToAudio(PromptSystem.didnt_understand_try_again)",
                "operands": [
                  {
                    "sysref": {
                      "pos": 9,
                      "text": "PromptSystem.didnt_understand_try_again",
                      "type": "pmt",
                      "val": "__didntunderstandtryagain__"
                    }
                  }
                ],
                "type": "aud"
              }
            },
            "text": "ToAudio(PromptSystem.didnt_understand_try_again)",
            "type": "aud",
            "uiMetaData": {
              "sequenceItems": [
                {
                  "type": 1,
                  "parameter": "__didntunderstandtryagain__",
                  "name": "PromptSystem.didnt_understand_try_again",
                  "isSystem": true
                }
              ],
              "customExpressionMode": false
            },
            "metaData": {
              "references": [
                {
                  "id": "__didntunderstandtryagain__",
                  "type": "pmt",
                  "isSysRef": true,
                  "name": "PromptSystem.didnt_understand_try_again"
                }
              ]
            }
          },
          "cases": [],
          "bargeIn": "Enabled",
          "bargeInDuration": {
            "config": {
              "lit": {
                "pos": 1,
                "text": "P0D0H0M0S500F",
                "type": "dur"
              }
            },
            "text": "P0D0H0M0S500F",
            "type": "dur",
            "uiMetaData": {
              "mode": 1
            },
            "metaData": {}
          }
        },
        {
          "defaultAudio": {
            "config": {
              "ToAudio": {
                "pos": 1,
                "text": "ToAudio(PromptSystem.please_try_again)",
                "operands": [
                  {
                    "sysref": {
                      "pos": 9,
                      "text": "PromptSystem.please_try_again",
                      "type": "pmt",
                      "val": "__pleasetryagain__"
                    }
                  }
                ],
                "type": "aud"
              }
            },
            "text": "ToAudio(PromptSystem.please_try_again)",
            "type": "aud",
            "uiMetaData": {
              "sequenceItems": [
                {
                  "type": 1,
                  "parameter": "__pleasetryagain__",
                  "name": "PromptSystem.please_try_again",
                  "isSystem": true
                }
              ],
              "customExpressionMode": false
            },
            "metaData": {
              "references": [
                {
                  "id": "__pleasetryagain__",
                  "type": "pmt",
                  "isSysRef": true,
                  "name": "PromptSystem.please_try_again"
                }
              ]
            }
          },
          "cases": [],
          "bargeIn": "Enabled",
          "bargeInDuration": {
            "config": {
              "lit": {
                "pos": 1,
                "text": "P0D0H0M0S500F",
                "type": "dur"
              }
            },
            "text": "P0D0H0M0S500F",
            "type": "dur",
            "uiMetaData": {
              "mode": 1
            },
            "metaData": {}
          }
        },
        {
          "defaultAudio": {
            "config": {
              "ToAudio": {
                "pos": 1,
                "text": "ToAudio(PromptSystem.didnt_get_that_try_again)",
                "operands": [
                  {
                    "sysref": {
                      "pos": 9,
                      "text": "PromptSystem.didnt_get_that_try_again",
                      "type": "pmt",
                      "val": "__didntgetthattryagain__"
                    }
                  }
                ],
                "type": "aud"
              }
            },
            "text": "ToAudio(PromptSystem.didnt_get_that_try_again)",
            "type": "aud",
            "uiMetaData": {
              "sequenceItems": [
                {
                  "type": 1,
                  "parameter": "__didntgetthattryagain__",
                  "name": "PromptSystem.didnt_get_that_try_again",
                  "isSystem": true
                }
              ],
              "customExpressionMode": false
            },
            "metaData": {
              "references": [
                {
                  "id": "__didntgetthattryagain__",
                  "type": "pmt",
                  "isSysRef": true,
                  "name": "PromptSystem.didnt_get_that_try_again"
                }
              ]
            }
          },
          "cases": [],
          "bargeIn": "Enabled",
          "bargeInDuration": {
            "config": {
              "lit": {
                "pos": 1,
                "text": "P0D0H0M0S500F",
                "type": "dur"
              }
            },
            "text": "P0D0H0M0S500F",
            "type": "dur",
            "uiMetaData": {
              "mode": 1
            },
            "metaData": {}
          }
        },
        {
          "defaultAudio": {
            "config": {
              "ToAudio": {
                "pos": 1,
                "text": "ToAudio(PromptSystem.having_trouble_understanding)",
                "operands": [
                  {
                    "sysref": {
                      "pos": 9,
                      "text": "PromptSystem.having_trouble_understanding",
                      "type": "pmt",
                      "val": "__havingtroubleunderstanding__"
                    }
                  }
                ],
                "type": "aud"
              }
            },
            "text": "ToAudio(PromptSystem.having_trouble_understanding)",
            "type": "aud",
            "uiMetaData": {
              "sequenceItems": [
                {
                  "type": 1,
                  "parameter": "__havingtroubleunderstanding__",
                  "name": "PromptSystem.having_trouble_understanding",
                  "isSystem": true
                }
              ],
              "customExpressionMode": false
            },
            "metaData": {
              "references": [
                {
                  "id": "__havingtroubleunderstanding__",
                  "type": "pmt",
                  "isSysRef": true,
                  "name": "PromptSystem.having_trouble_understanding"
                }
              ]
            }
          },
          "cases": [],
          "bargeIn": "Enabled",
          "bargeInDuration": {
            "config": {
              "lit": {
                "pos": 1,
                "text": "P0D0H0M0S500F",
                "type": "dur"
              }
            },
            "text": "P0D0H0M0S500F",
            "type": "dur",
            "uiMetaData": {
              "mode": 1
            },
            "metaData": {}
          }
        }
      ]
    },
    "Menu": {
      "promptRepeatCount": {
        "config": {
          "lit": {
            "pos": 1,
            "text": "10",
            "type": "int"
          }
        },
        "text": "10",
        "type": "int",
        "uiMetaData": {
          "mode": 1
        },
        "metaData": {}
      },
      "promptRepeatDelay": {
        "config": {
          "lit": {
            "pos": 1,
            "text": "P0D0H0M10S0F",
            "type": "dur"
          }
        },
        "text": "P0D0H0M10S0F",
        "type": "dur",
        "uiMetaData": {
          "mode": 1
        },
        "metaData": {}
      },
      "extensionDialingDelay": {
        "config": {
          "lit": {
            "pos": 1,
            "text": "P0D0H0M1S0F",
            "type": "dur"
          }
        },
        "text": "P0D0H0M1S0F",
        "type": "dur",
        "uiMetaData": {
          "mode": 1
        },
        "metaData": {}
      },
      "useExtensionDialing": {
        "config": {
          "lit": {
            "pos": 1,
            "text": "true",
            "type": "bln"
          }
        },
        "text": "true",
        "type": "bln",
        "uiMetaData": {
          "mode": 1
        },
        "metaData": {}
      }
    }
  },
  "disableAsr": {
    "config": {
      "lit": {
        "pos": 1,
        "text": "true",
        "type": "bln"
      }
    },
    "text": "true",
    "type": "bln",
    "uiMetaData": {
      "mode": 1
    },
    "metaData": {}
  },
  "disableAsrCompanyDirectory": {
    "config": {
      "lit": {
        "pos": 1,
        "text": "false",
        "type": "bln"
      }
    },
    "text": "false",
    "type": "bln",
    "uiMetaData": {
      "mode": 1
    },
    "metaData": {}
  },
  "errorHandling": {
    "audio": {
      "defaultAudio": {
        "config": {
          "ToAudioTTS": {
            "pos": 1,
            "text": "ToAudioTTS(\"Sorry, an error occurred. Please try your call again.\")",
            "operands": [
              {
                "lit": {
                  "pos": 12,
                  "text": "Sorry, an error occurred. Please try your call again.",
                  "type": "str"
                }
              }
            ],
            "type": "aud"
          }
        },
        "text": "ToAudioTTS(\"Sorry, an error occurred. Please try your call again.\")",
        "type": "aud",
        "uiMetaData": {
          "sequenceItems": [
            {
              "type": 0,
              "parameter": "Sorry, an error occurred. Please try your call again."
            }
          ],
          "customExpressionMode": false,
          "optional": true
        },
        "metaData": {}
      },
      "cases": [],
      "bargeIn": "Enabled",
      "bargeInDuration": {
        "config": {
          "lit": {
            "pos": 1,
            "text": "P0D0H0M0S500F",
            "type": "dur"
          }
        },
        "text": "P0D0H0M0S500F",
        "type": "dur",
        "uiMetaData": {
          "mode": 1
        },
        "metaData": {}
      }
    },
    "handlingType": "Disconnect",
    "queue": {
      "config": {
        "emp": {
          "pos": 1,
          "text": "",
          "type": "que"
        }
      },
      "text": "",
      "type": "que",
      "uiMetaData": {
        "mode": 1
      },
      "metaData": {}
    }
  },
  "initialPrompts": {
    "defaultAudio": {
      "config": {
        "ToAudio": {
          "pos": 1,
          "text": "ToAudio(Prompt.AUGenericWelcome)",
          "operands": [
            {
              "ref": {
                "pos": 9,
                "text": "Prompt.AUGenericWelcome",
                "type": "pmt",
                "val": "bfc3f9b6-8b2b-45ee-8652-0a939e617753"
              }
            }
          ],
          "type": "aud"
        }
      },
      "text": "ToAudio(Prompt.AUGenericWelcome)",
      "type": "aud",
      "uiMetaData": {
        "sequenceItems": [
          {
            "type": 1,
            "name": "Prompt.AUGenericWelcome",
            "isSystem": false,
            "expressionName": "Prompt.AUGenericWelcome",
            "parameter": "bfc3f9b6-8b2b-45ee-8652-0a939e617753"
          }
        ],
        "customExpressionMode": false,
        "optional": true
      },
      "metaData": {
        "references": [
          {
            "id": "bfc3f9b6-8b2b-45ee-8652-0a939e617753",
            "type": "pmt",
            "isSysRef": false,
            "name": "Prompt.AUGenericWelcome"
          }
        ]
      }
    },
    "cases": [],
    "bargeIn": "Enabled",
    "bargeInDuration": {
      "config": {
        "lit": {
          "pos": 1,
          "text": "P0D0H0M0S500F",
          "type": "dur"
        }
      },
      "text": "P0D0H0M0S500F",
      "type": "dur",
      "uiMetaData": {
        "mode": 1
      },
      "metaData": {}
    }
  },
  "speechRecCompanyDirectory": {
    "config": {
      "lit": {
        "pos": 1,
        "text": "false",
        "type": "bln"
      }
    },
    "text": "false",
    "type": "bln",
    "uiMetaData": {
      "mode": 1
    },
    "metaData": {}
  },
  "speechRecEngine": {
    "config": {
      "lit": {
        "pos": 1,
        "text": "",
        "type": "str"
      }
    },
    "text": "",
    "type": "str",
    "uiMetaData": {
      "mode": 1
    },
    "metaData": {}
  },
  "supportedLanguageOptions": [
    {
      "fallbackOverride": "",
      "language": "en-AU",
      "languageSkill": {
        "config": {
          "lit": {
            "pos": 1,
            "text": "",
            "type": "lac"
          }
        },
        "text": "",
        "type": "lac",
        "uiMetaData": {
          "mode": 1
        },
        "metaData": {}
      }
    }
  ],
  "flowMetaData": {
    "features": [],
    "flowDocumentVersion": "1.1",
    "minimumServerVersion": "1.0"
  },
  "flowSequenceItemList": [
    {
      "startAction": "7472b020-33d8-438e-957c-d8b36be4aad2",
      "trackingId": 34,
      "id": "2c6645f4-eca3-4fe6-ac94-07c57c2877a7",
      "name": "Get Salesforce Contact",
      "__type": "Task",
      "paths": [
        {
          "label": "Default",
          "outputId": "__DEFAULT__"
        }
      ],
      "actionList": [
        {
          "nextAction": "284c3ee7-f0aa-4121-9865-757453bfb135",
          "trackingId": 35,
          "id": "7472b020-33d8-438e-957c-d8b36be4aad2",
          "name": "Play CLI and DNIS",
          "__type": "PlayAudioAction",
          "prompts": {
            "defaultAudio": {
              "config": {
                "Append": {
                  "pos": 1,
                  "text": "Append(ToAudioTTS(\"Your telephone number is.\"), ToAudioPhoneNumber(Call.Ani), ToAudioTTS(\"The number you dialed is.\"), ToAudioPhoneNumber(Call.CalledAddress), ToAudioTTS(\"Now we use Salesforce to retrieve the contact details.\"))",
                  "operands": [
                    {
                      "ToAudioTTS": {
                        "pos": 8,
                        "text": "ToAudioTTS(\"Your telephone number is.\")",
                        "operands": [
                          {
                            "lit": {
                              "pos": 19,
                              "text": "Your telephone number is.",
                              "type": "str"
                            }
                          }
                        ],
                        "type": "aud"
                      }
                    },
                    {
                      "ToAudioPhoneNumber": {
                        "pos": 49,
                        "text": "ToAudioPhoneNumber(Call.Ani)",
                        "operands": [
                          {
                            "sysref": {
                              "pos": 68,
                              "text": "Call.Ani",
                              "type": "str",
                              "val": "__CALL_ANI__"
                            }
                          }
                        ],
                        "type": "aud"
                      }
                    },
                    {
                      "ToAudioTTS": {
                        "pos": 79,
                        "text": "ToAudioTTS(\"The number you dialed is.\")",
                        "operands": [
                          {
                            "lit": {
                              "pos": 90,
                              "text": "The number you dialed is.",
                              "type": "str"
                            }
                          }
                        ],
                        "type": "aud"
                      }
                    },
                    {
                      "ToAudioPhoneNumber": {
                        "pos": 120,
                        "text": "ToAudioPhoneNumber(Call.CalledAddress)",
                        "operands": [
                          {
                            "sysref": {
                              "pos": 139,
                              "text": "Call.CalledAddress",
                              "type": "str",
                              "val": "__CALL_DNIS__"
                            }
                          }
                        ],
                        "type": "aud"
                      }
                    },
                    {
                      "ToAudioTTS": {
                        "pos": 160,
                        "text": "ToAudioTTS(\"Now we use Salesforce to retrieve the contact details.\")",
                        "operands": [
                          {
                            "lit": {
                              "pos": 171,
                              "text": "Now we use Salesforce to retrieve the contact details.",
                              "type": "str"
                            }
                          }
                        ],
                        "type": "aud"
                      }
                    }
                  ],
                  "type": "aud"
                }
              },
              "text": "Append(ToAudioTTS(\"Your telephone number is.\"), ToAudioPhoneNumber(Call.Ani), ToAudioTTS(\"The number you dialed is.\"), ToAudioPhoneNumber(Call.CalledAddress), ToAudioTTS(\"Now we use Salesforce to retrieve the contact details.\"))",
              "type": "aud",
              "uiMetaData": {
                "sequenceItems": [
                  {
                    "type": 0,
                    "parameter": "Your telephone number is."
                  },
                  {
                    "type": 2,
                    "expressionFormat": "ToAudioPhoneNumber(%s)",
                    "functionOverloadIds": [
                      "Audio_ONE ToAudioPhoneNumber(String_ONE)"
                    ],
                    "variableId": "__CALL_ANI__",
                    "parameter": "Call.Ani",
                    "parameter2": ""
                  },
                  {
                    "type": 0,
                    "parameter": "The number you dialed is."
                  },
                  {
                    "type": 2,
                    "expressionFormat": "ToAudioPhoneNumber(%s)",
                    "functionOverloadIds": [
                      "Audio_ONE ToAudioPhoneNumber(String_ONE)"
                    ],
                    "variableId": "__CALL_DNIS__",
                    "parameter": "Call.CalledAddress",
                    "parameter2": ""
                  },
                  {
                    "type": 0,
                    "parameter": "Now we use Salesforce to retrieve the contact details."
                  }
                ],
                "customExpressionMode": false
              },
              "metaData": {
                "references": [
                  {
                    "id": "__CALL_ANI__",
                    "type": "str",
                    "isSysRef": true,
                    "name": "Call.Ani"
                  },
                  {
                    "id": "__CALL_DNIS__",
                    "type": "str",
                    "isSysRef": true,
                    "name": "Call.CalledAddress"
                  }
                ]
              }
            },
            "cases": [],
            "bargeIn": "Enabled",
            "bargeInDuration": {
              "config": {
                "lit": {
                  "pos": 1,
                  "text": "P0D0H0M0S500F",
                  "type": "dur"
                }
              },
              "text": "P0D0H0M0S500F",
              "type": "dur",
              "uiMetaData": {
                "mode": 1
              },
              "metaData": {}
            }
          }
        },
        {
          "nextAction": "e24bc584-8441-4e66-96ee-3fcd3cbc95eb",
          "trackingId": 37,
          "id": "a4e7632c-9502-4d89-b6d4-6129cc776aa3",
          "name": "Play Variables",
          "__type": "PlayAudioAction",
          "prompts": {
            "defaultAudio": {
              "config": {
                "Append": {
                  "pos": 1,
                  "text": "Append(ToAudioTTS(\"The customer's telephone is now in a CLI variable.\"), ToAudioPhoneNumber(Task.CLI))",
                  "operands": [
                    {
                      "ToAudioTTS": {
                        "pos": 8,
                        "text": "ToAudioTTS(\"The customer's telephone is now in a CLI variable.\")",
                        "operands": [
                          {
                            "lit": {
                              "pos": 19,
                              "text": "The customer's telephone is now in a CLI variable.",
                              "type": "str"
                            }
                          }
                        ],
                        "type": "aud"
                      }
                    },
                    {
                      "ToAudioPhoneNumber": {
                        "pos": 74,
                        "text": "ToAudioPhoneNumber(Task.CLI)",
                        "operands": [
                          {
                            "ref": {
                              "pos": 93,
                              "text": "Task.CLI",
                              "type": "str",
                              "val": "23fb09b6-3750-468a-8d3a-92d22b12f04d"
                            }
                          }
                        ],
                        "type": "aud"
                      }
                    }
                  ],
                  "type": "aud"
                }
              },
              "text": "Append(ToAudioTTS(\"The customer's telephone is now in a CLI variable.\"), ToAudioPhoneNumber(Task.CLI))",
              "type": "aud",
              "uiMetaData": {
                "sequenceItems": [
                  {
                    "type": 0,
                    "parameter": "The customer's telephone is now in a CLI variable."
                  },
                  {
                    "type": 2,
                    "expressionFormat": "ToAudioPhoneNumber(%s)",
                    "functionOverloadIds": [
                      "Audio_ONE ToAudioPhoneNumber(String_ONE)"
                    ],
                    "variableId": "23fb09b6-3750-468a-8d3a-92d22b12f04d",
                    "parameter": "Task.CLI"
                  }
                ],
                "customExpressionMode": false
              },
              "metaData": {
                "references": [
                  {
                    "id": "23fb09b6-3750-468a-8d3a-92d22b12f04d",
                    "type": "str",
                    "isSysRef": false,
                    "name": "Task.CLI"
                  }
                ]
              }
            },
            "cases": [],
            "bargeIn": "Enabled",
            "bargeInDuration": {
              "config": {
                "lit": {
                  "pos": 1,
                  "text": "P0D0H0M0S500F",
                  "type": "dur"
                }
              },
              "text": "P0D0H0M0S500F",
              "type": "dur",
              "uiMetaData": {
                "mode": 1
              },
              "metaData": {}
            }
          }
        },
        {
          "actionName": "GetContactByPhoneNumber",
          "id": "e24bc584-8441-4e66-96ee-3fcd3cbc95eb",
          "useSuggestedTimeout": true,
          "nextAction": "8d3e7142-7410-41a8-be87-526dcb35fac4",
          "trackingId": 47,
          "name": "Salesforce Data Dip",
          "uiMetaData": {
            "hasDeletedVersion": true
          },
          "_errorData": {
            "config": {
              "emp": {
                "pos": 1,
                "text": "",
                "type": "str"
              }
            },
            "text": "",
            "type": "str",
            "uiMetaData": {
              "mode": 2
            },
            "metaData": {}
          },
          "_httpStatusCode": {
            "config": {
              "emp": {
                "pos": 1,
                "text": "",
                "type": "dec"
              }
            },
            "text": "",
            "type": "dec",
            "uiMetaData": {
              "mode": 2
            },
            "metaData": {}
          },
          "_status": {
            "config": {
              "emp": {
                "pos": 1,
                "text": "",
                "type": "str"
              }
            },
            "text": "",
            "type": "str",
            "uiMetaData": {
              "mode": 2
            },
            "metaData": {}
          },
          "__type": "BridgeServerAction",
          "errorData": {
            "config": {
              "emp": {
                "pos": 1,
                "text": "",
                "type": "str"
              }
            },
            "text": "",
            "type": "str",
            "uiMetaData": {
              "mode": 2
            },
            "metaData": {}
          },
          "httpStatusCode": {
            "config": {
              "emp": {
                "pos": 1,
                "text": "",
                "type": "dec"
              }
            },
            "text": "",
            "type": "dec",
            "uiMetaData": {
              "mode": 2
            },
            "metaData": {}
          },
          "inputs": [
            {
              "name": "PhoneNumber",
              "value": {
                "config": {
                  "ref": {
                    "pos": 1,
                    "text": "Task.CLI",
                    "type": "str",
                    "val": "23fb09b6-3750-468a-8d3a-92d22b12f04d"
                  }
                },
                "text": "Task.CLI",
                "type": "str",
                "uiMetaData": {
                  "mode": 0
                },
                "metaData": {
                  "references": [
                    {
                      "id": "23fb09b6-3750-468a-8d3a-92d22b12f04d",
                      "type": "str",
                      "isSysRef": false,
                      "name": "Task.CLI"
                    }
                  ]
                }
              }
            },
            {
              "name": "CustomAttribute",
              "value": {
                "config": {
                  "lit": {
                    "pos": 1,
                    "text": "",
                    "type": "str"
                  }
                },
                "text": "",
                "type": "str",
                "uiMetaData": {
                  "mode": 1
                },
                "metaData": {}
              }
            }
          ],
          "message": {
            "config": {
              "emp": {
                "pos": 1,
                "text": "",
                "type": "str"
              }
            },
            "text": "",
            "type": "str",
            "uiMetaData": {
              "mode": 2
            },
            "metaData": {}
          },
          "outputs": [
            {
              "name": "Contact.Address.City",
              "value": {
                "config": {
                  "emp": {
                    "pos": 1,
                    "text": "",
                    "type": "str"
                  }
                },
                "text": "",
                "type": "str",
                "uiMetaData": {
                  "mode": 2
                },
                "metaData": {}
              }
            },
            {
              "name": "Contact.Address.Country",
              "value": {
                "config": {
                  "emp": {
                    "pos": 1,
                    "text": "",
                    "type": "str"
                  }
                },
                "text": "",
                "type": "str",
                "uiMetaData": {
                  "mode": 2
                },
                "metaData": {}
              }
            },
            {
              "name": "Contact.Address.Line1",
              "value": {
                "config": {
                  "emp": {
                    "pos": 1,
                    "text": "",
                    "type": "str"
                  }
                },
                "text": "",
                "type": "str",
                "uiMetaData": {
                  "mode": 2
                },
                "metaData": {}
              }
            },
            {
              "name": "Contact.Address.Line2",
              "value": {
                "config": {
                  "emp": {
                    "pos": 1,
                    "text": "",
                    "type": "str"
                  }
                },
                "text": "",
                "type": "str",
                "uiMetaData": {
                  "mode": 2
                },
                "metaData": {}
              }
            },
            {
              "name": "Contact.Address.Line3",
              "value": {
                "config": {
                  "emp": {
                    "pos": 1,
                    "text": "",
                    "type": "str"
                  }
                },
                "text": "",
                "type": "str",
                "uiMetaData": {
                  "mode": 2
                },
                "metaData": {}
              }
            },
            {
              "name": "Contact.Address.PostalCode",
              "value": {
                "config": {
                  "emp": {
                    "pos": 1,
                    "text": "",
                    "type": "str"
                  }
                },
                "text": "",
                "type": "str",
                "uiMetaData": {
                  "mode": 2
                },
                "metaData": {}
              }
            },
            {
              "name": "Contact.Address.State",
              "value": {
                "config": {
                  "emp": {
                    "pos": 1,
                    "text": "",
                    "type": "str"
                  }
                },
                "text": "",
                "type": "str",
                "uiMetaData": {
                  "mode": 2
                },
                "metaData": {}
              }
            },
            {
              "name": "Contact.Address.Type",
              "value": {
                "config": {
                  "emp": {
                    "pos": 1,
                    "text": "",
                    "type": "int"
                  }
                },
                "text": "",
                "type": "int",
                "uiMetaData": {
                  "mode": 2
                },
                "metaData": {}
              }
            },
            {
              "name": "Contact.EmailAddresses.EmailAddress.EmailAddress",
              "value": {
                "config": {
                  "emp": {
                    "pos": 1,
                    "text": "",
                    "type": "str_coll"
                  }
                },
                "text": "",
                "type": "str_coll",
                "uiMetaData": {
                  "mode": 2
                },
                "metaData": {}
              }
            },
            {
              "name": "Contact.EmailAddresses.EmailAddress.EmailType",
              "value": {
                "config": {
                  "emp": {
                    "pos": 1,
                    "text": "",
                    "type": "int_coll"
                  }
                },
                "text": "",
                "type": "int_coll",
                "uiMetaData": {
                  "mode": 2
                },
                "metaData": {}
              }
            },
            {
              "name": "Contact.FullName",
              "value": {
                "config": {
                  "ref": {
                    "pos": 1,
                    "text": "Task.ContactName",
                    "type": "str",
                    "val": "bf7c53e1-6572-4730-9022-39ac1cbf9762"
                  }
                },
                "text": "Task.ContactName",
                "type": "str",
                "uiMetaData": {
                  "mode": 2
                },
                "metaData": {
                  "references": [
                    {
                      "id": "bf7c53e1-6572-4730-9022-39ac1cbf9762",
                      "type": "str",
                      "isSysRef": false,
                      "name": "Task.ContactName"
                    }
                  ]
                }
              }
            },
            {
              "name": "Contact.FirstName",
              "value": {
                "config": {
                  "ref": {
                    "pos": 1,
                    "text": "Flow.Fullname",
                    "type": "str",
                    "val": "49fb79cb-3cac-4197-b130-20e1fb8fa7ef"
                  }
                },
                "text": "Flow.Fullname",
                "type": "str",
                "uiMetaData": {
                  "mode": 2
                },
                "metaData": {
                  "references": [
                    {
                      "id": "49fb79cb-3cac-4197-b130-20e1fb8fa7ef",
                      "type": "str",
                      "isSysRef": false,
                      "name": "Flow.Fullname"
                    }
                  ]
                }
              }
            },
            {
              "name": "Contact.Id",
              "value": {
                "config": {
                  "ref": {
                    "pos": 1,
                    "text": "Task.ContactID",
                    "type": "str",
                    "val": "619d545c-6c16-4da8-b647-6887b60ee718"
                  }
                },
                "text": "Task.ContactID",
                "type": "str",
                "uiMetaData": {
                  "mode": 2
                },
                "metaData": {
                  "references": [
                    {
                      "id": "619d545c-6c16-4da8-b647-6887b60ee718",
                      "type": "str",
                      "isSysRef": false,
                      "name": "Task.ContactID"
                    }
                  ]
                }
              }
            },
            {
              "name": "Contact.LastName",
              "value": {
                "config": {
                  "emp": {
                    "pos": 1,
                    "text": "",
                    "type": "str"
                  }
                },
                "text": "",
                "type": "str",
                "uiMetaData": {
                  "mode": 2
                },
                "metaData": {}
              }
            },
            {
              "name": "Contact.PhoneNumbers.PhoneNumber.Number",
              "value": {
                "config": {
                  "emp": {
                    "pos": 1,
                    "text": "",
                    "type": "str_coll"
                  }
                },
                "text": "",
                "type": "str_coll",
                "uiMetaData": {
                  "mode": 2
                },
                "metaData": {}
              }
            },
            {
              "name": "Contact.PhoneNumbers.PhoneNumber.PhoneType",
              "value": {
                "config": {
                  "emp": {
                    "pos": 1,
                    "text": "",
                    "type": "int_coll"
                  }
                },
                "text": "",
                "type": "int_coll",
                "uiMetaData": {
                  "mode": 2
                },
                "metaData": {}
              }
            },
            {
              "name": "Contact.CustomAttribute",
              "value": {
                "config": {
                  "emp": {
                    "pos": 1,
                    "text": "",
                    "type": "str"
                  }
                },
                "text": "",
                "type": "str",
                "uiMetaData": {
                  "mode": 2
                },
                "metaData": {}
              }
            }
          ],
          "paths": [
            {
              "nextActionId": "0072c526-1dec-4966-8490-d720fa6ba333",
              "label": "Success",
              "outputId": "__SUCCESS__"
            },
            {
              "nextActionId": "8271b043-eccf-430f-8418-f6853507a687",
              "label": "Failure",
              "outputId": "__FAILURE__"
            },
            {
              "nextActionId": "771b927e-a308-466e-bb44-0ab5773e9262",
              "label": "Timeout",
              "outputId": "__TIMEOUT__"
            }
          ],
          "status": {
            "config": {
              "emp": {
                "pos": 1,
                "text": "",
                "type": "str"
              }
            },
            "text": "",
            "type": "str",
            "uiMetaData": {
              "mode": 2
            },
            "metaData": {}
          },
          "timeout": {
            "config": {
              "lit": {
                "pos": 1,
                "text": "P0D0H0M5S0F",
                "type": "dur"
              }
            },
            "text": "P0D0H0M5S0F",
            "type": "dur",
            "uiMetaData": {
              "mode": 1
            },
            "metaData": {}
          }
        },
        {
          "nextAction": "32e3b732-e2ce-4610-8f65-3d97de5a3dbc",
          "trackingId": 48,
          "id": "0072c526-1dec-4966-8490-d720fa6ba333",
          "name": "Success",
          "__type": "PlayAudioAction",
          "prompts": {
            "defaultAudio": {
              "config": {
                "ToAudioTTS": {
                  "pos": 1,
                  "text": "ToAudioTTS(\"SUCCESS.\")",
                  "operands": [
                    {
                      "lit": {
                        "pos": 12,
                        "text": "SUCCESS.",
                        "type": "str"
                      }
                    }
                  ],
                  "type": "aud"
                }
              },
              "text": "ToAudioTTS(\"SUCCESS.\")",
              "type": "aud",
              "uiMetaData": {
                "sequenceItems": [
                  {
                    "type": 0,
                    "parameter": "SUCCESS."
                  }
                ],
                "customExpressionMode": false
              },
              "metaData": {}
            },
            "cases": [],
            "bargeIn": "Enabled",
            "bargeInDuration": {
              "config": {
                "lit": {
                  "pos": 1,
                  "text": "P0D0H0M0S500F",
                  "type": "dur"
                }
              },
              "text": "P0D0H0M0S500F",
              "type": "dur",
              "uiMetaData": {
                "mode": 1
              },
              "metaData": {}
            }
          }
        },
        {
          "trackingId": 49,
          "id": "8271b043-eccf-430f-8418-f6853507a687",
          "name": "Failure",
          "__type": "PlayAudioAction",
          "prompts": {
            "defaultAudio": {
              "config": {
                "ToAudioTTS": {
                  "pos": 1,
                  "text": "ToAudioTTS(\"FAILED\")",
                  "operands": [
                    {
                      "lit": {
                        "pos": 12,
                        "text": "FAILED",
                        "type": "str"
                      }
                    }
                  ],
                  "type": "aud"
                }
              },
              "text": "ToAudioTTS(\"FAILED\")",
              "type": "aud",
              "uiMetaData": {
                "sequenceItems": [
                  {
                    "type": 0,
                    "parameter": "FAILED"
                  }
                ],
                "customExpressionMode": false
              },
              "metaData": {}
            },
            "cases": [],
            "bargeIn": "Enabled",
            "bargeInDuration": {
              "config": {
                "lit": {
                  "pos": 1,
                  "text": "P0D0H0M0S500F",
                  "type": "dur"
                }
              },
              "text": "P0D0H0M0S500F",
              "type": "dur",
              "uiMetaData": {
                "mode": 1
              },
              "metaData": {}
            }
          }
        },
        {
          "trackingId": 50,
          "id": "771b927e-a308-466e-bb44-0ab5773e9262",
          "name": "Timeout",
          "__type": "PlayAudioAction",
          "prompts": {
            "defaultAudio": {
              "config": {
                "ToAudioTTS": {
                  "pos": 1,
                  "text": "ToAudioTTS(\"TIMED OUT\")",
                  "operands": [
                    {
                      "lit": {
                        "pos": 12,
                        "text": "TIMED OUT",
                        "type": "str"
                      }
                    }
                  ],
                  "type": "aud"
                }
              },
              "text": "ToAudioTTS(\"TIMED OUT\")",
              "type": "aud",
              "uiMetaData": {
                "sequenceItems": [
                  {
                    "type": 0,
                    "parameter": "TIMED OUT"
                  }
                ],
                "customExpressionMode": false
              },
              "metaData": {}
            },
            "cases": [],
            "bargeIn": "Enabled",
            "bargeInDuration": {
              "config": {
                "lit": {
                  "pos": 1,
                  "text": "P0D0H0M0S500F",
                  "type": "dur"
                }
              },
              "text": "P0D0H0M0S500F",
              "type": "dur",
              "uiMetaData": {
                "mode": 1
              },
              "metaData": {}
            }
          }
        },
        {
          "trackingId": 55,
          "id": "d5b51680-0fc5-4d04-8203-3e473892d106",
          "name": "Disconnect",
          "__type": "DisconnectAction"
        },
        {
          "nextAction": "a4e7632c-9502-4d89-b6d4-6129cc776aa3",
          "trackingId": 94,
          "id": "284c3ee7-f0aa-4121-9865-757453bfb135",
          "name": "Update Data",
          "__type": "UpdateVariableAction",
          "variables": [
            {
              "expression": {
                "config": {
                  "sysref": {
                    "pos": 1,
                    "text": "Call.Ani",
                    "type": "str",
                    "val": "__CALL_ANI__"
                  }
                },
                "text": "Call.Ani",
                "type": "str",
                "uiMetaData": {
                  "mode": 0
                },
                "metaData": {
                  "references": [
                    {
                      "id": "__CALL_ANI__",
                      "type": "str",
                      "isSysRef": true,
                      "name": "Call.Ani"
                    }
                  ]
                }
              },
              "variable": {
                "config": {
                  "ref": {
                    "pos": 1,
                    "text": "Task.CLI",
                    "type": "str",
                    "val": "23fb09b6-3750-468a-8d3a-92d22b12f04d"
                  }
                },
                "text": "Task.CLI",
                "type": "str",
                "uiMetaData": {
                  "mode": 2
                },
                "metaData": {
                  "references": [
                    {
                      "id": "23fb09b6-3750-468a-8d3a-92d22b12f04d",
                      "type": "str",
                      "isSysRef": false,
                      "name": "Task.CLI"
                    }
                  ]
                }
              }
            },
            {
              "expression": {
                "config": {
                  "nul": {
                    "pos": 1,
                    "text": "",
                    "type": "str"
                  }
                },
                "text": "NOT_SET",
                "type": "str",
                "uiMetaData": {
                  "mode": 0
                },
                "metaData": {}
              },
              "variable": {
                "config": {
                  "ref": {
                    "pos": 1,
                    "text": "Task.ContactID",
                    "type": "str",
                    "val": "619d545c-6c16-4da8-b647-6887b60ee718"
                  }
                },
                "text": "Task.ContactID",
                "type": "str",
                "uiMetaData": {
                  "mode": 2
                },
                "metaData": {
                  "references": [
                    {
                      "id": "619d545c-6c16-4da8-b647-6887b60ee718",
                      "type": "str",
                      "isSysRef": false,
                      "name": "Task.ContactID"
                    }
                  ]
                }
              }
            },
            {
              "expression": {
                "config": {
                  "nul": {
                    "pos": 1,
                    "text": "",
                    "type": "str"
                  }
                },
                "text": "NOT_SET",
                "type": "str",
                "uiMetaData": {
                  "mode": 0
                },
                "metaData": {}
              },
              "variable": {
                "config": {
                  "ref": {
                    "pos": 1,
                    "text": "Task.ContactName",
                    "type": "str",
                    "val": "bf7c53e1-6572-4730-9022-39ac1cbf9762"
                  }
                },
                "text": "Task.ContactName",
                "type": "str",
                "uiMetaData": {
                  "mode": 2
                },
                "metaData": {
                  "references": [
                    {
                      "id": "bf7c53e1-6572-4730-9022-39ac1cbf9762",
                      "type": "str",
                      "isSysRef": false,
                      "name": "Task.ContactName"
                    }
                  ]
                }
              }
            }
          ]
        },
        {
          "inQueueFlowId": "037f2416-0bfc-4172-afe1-18a8989cae7e",
          "inQueueFlowName": "Default In-Queue Flow",
          "enableInQueueFlow": true,
          "useDefaultHandling": true,
          "nextAction": "d5b51680-0fc5-4d04-8203-3e473892d106",
          "trackingId": 95,
          "id": "8d3e7142-7410-41a8-be87-526dcb35fac4",
          "name": "Transfer to ACD",
          "__type": "TransferPureMatchAction",
          "languageSkill": {
            "config": {
              "emp": {
                "pos": 1,
                "text": "",
                "type": "lac"
              }
            },
            "text": "",
            "type": "lac",
            "uiMetaData": {
              "mode": 0
            },
            "metaData": {}
          },
          "priority": {
            "config": {
              "lit": {
                "pos": 1,
                "text": "0",
                "type": "int"
              }
            },
            "text": "0",
            "type": "int",
            "uiMetaData": {
              "mode": 1
            },
            "metaData": {}
          },
          "queues": [
            {
              "config": {
                "lit": {
                  "pos": 1,
                  "text": "OzInbound_Q",
                  "type": "que",
                  "val": "3c61d082-33b9-41e4-9d5e-b4def04448b0"
                }
              },
              "text": "OzInbound_Q",
              "type": "que",
              "uiMetaData": {
                "mode": 1
              },
              "metaData": {}
            }
          ],
          "skills": [],
          "paths": [
            {
              "label": "Failure",
              "outputId": "__FAILURE__"
            }
          ],
          "preTransferAudio": {
            "defaultAudio": {
              "config": {
                "ToAudioTTS": {
                  "pos": 1,
                  "text": "ToAudioTTS(\"Transferring Now\")",
                  "operands": [
                    {
                      "lit": {
                        "pos": 12,
                        "text": "Transferring Now",
                        "type": "str"
                      }
                    }
                  ],
                  "type": "aud"
                }
              },
              "text": "ToAudioTTS(\"Transferring Now\")",
              "type": "aud",
              "uiMetaData": {
                "sequenceItems": [
                  {
                    "type": 0,
                    "parameter": "Transferring Now"
                  }
                ],
                "customExpressionMode": false
              },
              "metaData": {}
            },
            "cases": [],
            "bargeIn": "Enabled",
            "bargeInDuration": {
              "config": {
                "lit": {
                  "pos": 1,
                  "text": "P0D0H0M0S500F",
                  "type": "dur"
                }
              },
              "text": "P0D0H0M0S500F",
              "type": "dur",
              "uiMetaData": {
                "mode": 1
              },
              "metaData": {}
            }
          },
          "failureTransferAudio": {
            "defaultAudio": {
              "text": "",
              "type": "aud",
              "uiMetaData": {
                "sequenceItems": [
                  {
                    "type": 0,
                    "parameter": ""
                  }
                ],
                "customExpressionMode": false
              }
            },
            "cases": [],
            "bargeIn": "Enabled",
            "bargeInDuration": {
              "config": {
                "lit": {
                  "pos": 1,
                  "text": "P0D0H0M0S500F",
                  "type": "dur"
                }
              },
              "text": "P0D0H0M0S500F",
              "type": "dur",
              "uiMetaData": {
                "mode": 1
              },
              "metaData": {}
            }
          }
        },
        {
          "trackingId": 96,
          "id": "32e3b732-e2ce-4610-8f65-3d97de5a3dbc",
          "name": "Play Audio",
          "__type": "PlayAudioAction",
          "prompts": {
            "defaultAudio": {
              "config": {
                "Append": {
                  "pos": 1,
                  "text": "Append(ToAudioTTS(\"Contact Fullname Is\"), ToAudioTTS(Task.ContactName), ToAudioTTS(\"Contact Identifier\"), ToAudioTTS(Task.ContactID, Format.String.playChars))",
                  "operands": [
                    {
                      "ToAudioTTS": {
                        "pos": 8,
                        "text": "ToAudioTTS(\"Contact Fullname Is\")",
                        "operands": [
                          {
                            "lit": {
                              "pos": 19,
                              "text": "Contact Fullname Is",
                              "type": "str"
                            }
                          }
                        ],
                        "type": "aud"
                      }
                    },
                    {
                      "ToAudioTTS": {
                        "pos": 43,
                        "text": "ToAudioTTS(Task.ContactName)",
                        "operands": [
                          {
                            "ref": {
                              "pos": 54,
                              "text": "Task.ContactName",
                              "type": "str",
                              "val": "bf7c53e1-6572-4730-9022-39ac1cbf9762"
                            }
                          }
                        ],
                        "type": "aud"
                      }
                    },
                    {
                      "ToAudioTTS": {
                        "pos": 73,
                        "text": "ToAudioTTS(\"Contact Identifier\")",
                        "operands": [
                          {
                            "lit": {
                              "pos": 84,
                              "text": "Contact Identifier",
                              "type": "str"
                            }
                          }
                        ],
                        "type": "aud"
                      }
                    },
                    {
                      "ToAudioTTS": {
                        "pos": 107,
                        "text": "ToAudioTTS(Task.ContactID, Format.String.playChars)",
                        "operands": [
                          {
                            "ref": {
                              "pos": 118,
                              "text": "Task.ContactID",
                              "type": "str",
                              "val": "619d545c-6c16-4da8-b647-6887b60ee718"
                            }
                          },
                          {
                            ".": {
                              "pos": 147,
                              "text": "Format.String.playChars",
                              "operands": [
                                {
                                  "lit": {
                                    "pos": 147,
                                    "text": "stringPlayChars",
                                    "type": "str"
                                  }
                                },
                                {
                                  "sysref": {
                                    "pos": 134,
                                    "text": "Format.String",
                                    "type": "stc",
                                    "val": "__FORMAT_STRING__"
                                  }
                                }
                              ],
                              "type": "stf"
                            }
                          }
                        ],
                        "type": "aud"
                      }
                    }
                  ],
                  "type": "aud"
                }
              },
              "text": "Append(ToAudioTTS(\"Contact Fullname Is\"), ToAudioTTS(Task.ContactName), ToAudioTTS(\"Contact Identifier\"), ToAudioTTS(Task.ContactID, Format.String.playChars))",
              "type": "aud",
              "uiMetaData": {
                "sequenceItems": [
                  {
                    "type": 0,
                    "parameter": "Contact Fullname Is"
                  },
                  {
                    "type": 2,
                    "expressionFormat": "ToAudioTTS(%s)",
                    "functionOverloadIds": [
                      "Audio_ONE ToAudioTTS(String_ONE)"
                    ],
                    "variableId": "bf7c53e1-6572-4730-9022-39ac1cbf9762",
                    "parameter": "Task.ContactName"
                  },
                  {
                    "type": 0,
                    "parameter": "Contact Identifier"
                  },
                  {
                    "type": 2,
                    "expressionFormat": "ToAudioTTS(%s, Format.String.playChars)",
                    "functionOverloadIds": [
                      "Audio_ONE ToAudioTTS(String_ONE,StringFormat_ONE)"
                    ],
                    "variableId": "619d545c-6c16-4da8-b647-6887b60ee718",
                    "parameter": "Task.ContactID"
                  }
                ],
                "customExpressionMode": false
              },
              "metaData": {
                "references": [
                  {
                    "id": "bf7c53e1-6572-4730-9022-39ac1cbf9762",
                    "type": "str",
                    "isSysRef": false,
                    "name": "Task.ContactName"
                  },
                  {
                    "id": "619d545c-6c16-4da8-b647-6887b60ee718",
                    "type": "str",
                    "isSysRef": false,
                    "name": "Task.ContactID"
                  },
                  {
                    "id": "__FORMAT_STRING__",
                    "type": "stc",
                    "isSysRef": true,
                    "name": "Format.String"
                  }
                ]
              }
            },
            "cases": [],
            "bargeIn": "Enabled",
            "bargeInDuration": {
              "config": {
                "lit": {
                  "pos": 1,
                  "text": "P0D0H0M0S500F",
                  "type": "dur"
                }
              },
              "text": "P0D0H0M0S500F",
              "type": "dur",
              "uiMetaData": {
                "mode": 1
              },
              "metaData": {}
            }
          }
        }
      ],
      "variables": [
        {
          "enableInitialValue": false,
          "id": "23fb09b6-3750-468a-8d3a-92d22b12f04d",
          "isCollection": false,
          "isInternal": false,
          "isOutput": false,
          "isInput": false,
          "isSecure": false,
          "name": "Task.CLI",
          "version": "1.0",
          "__type": "StringVariable",
          "initialValue": {
            "config": {
              "emp": {
                "pos": 1,
                "text": "",
                "type": "str"
              }
            },
            "text": "",
            "type": "str",
            "uiMetaData": {
              "mode": 1
            },
            "metaData": {}
          }
        },
        {
          "enableInitialValue": false,
          "id": "619d545c-6c16-4da8-b647-6887b60ee718",
          "isCollection": false,
          "isInternal": false,
          "isOutput": false,
          "isInput": false,
          "isSecure": false,
          "name": "Task.ContactID",
          "version": "1.0",
          "__type": "StringVariable",
          "initialValue": {
            "config": {
              "emp": {
                "pos": 1,
                "text": "",
                "type": "str"
              }
            },
            "text": "",
            "type": "str",
            "uiMetaData": {
              "mode": 1
            },
            "metaData": {}
          }
        },
        {
          "enableInitialValue": false,
          "id": "bf7c53e1-6572-4730-9022-39ac1cbf9762",
          "isCollection": false,
          "isInternal": false,
          "isOutput": false,
          "isInput": false,
          "isSecure": false,
          "name": "Task.ContactName",
          "version": "1.0",
          "__type": "StringVariable",
          "initialValue": {
            "config": {
              "emp": {
                "pos": 1,
                "text": "",
                "type": "str"
              }
            },
            "text": "",
            "type": "str",
            "uiMetaData": {
              "mode": 1
            },
            "metaData": {}
          }
        }
      ]
    },
    {
      "startAction": "da400793-30a8-4e32-a883-b31732e91dfb",
      "trackingId": 85,
      "id": "40bc01f7-b958-4b94-8967-1d2b43bbef4a",
      "name": "Get Script",
      "__type": "Task",
      "paths": [
        {
          "label": "Default",
          "outputId": "__DEFAULT__"
        }
      ],
      "actionList": [
        {
          "nextAction": "01df0827-4395-458b-8a07-10351771a8ed",
          "trackingId": 87,
          "id": "da400793-30a8-4e32-a883-b31732e91dfb",
          "name": "SF_Data",
          "__type": "SetAttributesAction",
          "variables": [
            {
              "expression": {
                "config": {
                  "lit": {
                    "pos": 1,
                    "text": "/apex/DisplayPage",
                    "type": "str"
                  }
                },
                "text": "/apex/DisplayPage",
                "type": "str",
                "uiMetaData": {
                  "mode": 1
                },
                "metaData": {}
              },
              "variable": {
                "config": {
                  "lit": {
                    "pos": 1,
                    "text": "SF_URLPop",
                    "type": "str"
                  }
                },
                "text": "SF_URLPop",
                "type": "str",
                "uiMetaData": {
                  "mode": 1
                },
                "metaData": {}
              }
            }
          ]
        },
        {
          "trackingId": 88,
          "id": "25180e0d-db87-4068-b436-cd31514f7b2d",
          "name": "Disconnect",
          "__type": "DisconnectAction"
        },
        {
          "screenPopId": "58a574a0-a4ab-11e6-b25e-4f1c124e1cea",
          "screenPopName": "BaseQ",
          "nextAction": "50de39c4-a32a-472d-84b0-e0d312a43662",
          "trackingId": 91,
          "id": "01df0827-4395-458b-8a07-10351771a8ed",
          "name": "Agent Script",
          "uiMetaData": {},
          "__type": "ScreenPopAction",
          "inputs": []
        },
        {
          "inQueueFlowId": "037f2416-0bfc-4172-afe1-18a8989cae7e",
          "inQueueFlowName": "Default In-Queue Flow",
          "enableInQueueFlow": true,
          "useDefaultHandling": true,
          "nextAction": "25180e0d-db87-4068-b436-cd31514f7b2d",
          "trackingId": 92,
          "id": "50de39c4-a32a-472d-84b0-e0d312a43662",
          "name": "Transfer to ACD",
          "__type": "TransferPureMatchAction",
          "languageSkill": {
            "config": {
              "emp": {
                "pos": 1,
                "text": "",
                "type": "lac"
              }
            },
            "text": "",
            "type": "lac",
            "uiMetaData": {
              "mode": 0
            },
            "metaData": {}
          },
          "priority": {
            "config": {
              "lit": {
                "pos": 1,
                "text": "0",
                "type": "int"
              }
            },
            "text": "0",
            "type": "int",
            "uiMetaData": {
              "mode": 1
            },
            "metaData": {}
          },
          "queues": [
            {
              "config": {
                "lit": {
                  "pos": 1,
                  "text": "OzInbound_Q",
                  "type": "que",
                  "val": "3c61d082-33b9-41e4-9d5e-b4def04448b0"
                }
              },
              "text": "OzInbound_Q",
              "type": "que",
              "uiMetaData": {
                "mode": 1
              },
              "metaData": {}
            }
          ],
          "skills": [],
          "paths": [
            {
              "label": "Failure",
              "outputId": "__FAILURE__"
            }
          ],
          "preTransferAudio": {
            "defaultAudio": {
              "config": {
                "ToAudioBlank": {
                  "pos": 1,
                  "text": "ToAudioBlank(100)",
                  "operands": [
                    {
                      "lit": {
                        "pos": 14,
                        "text": "100",
                        "type": "int"
                      }
                    }
                  ],
                  "type": "aud"
                }
              },
              "text": "ToAudioBlank(100)",
              "type": "aud",
              "uiMetaData": {
                "sequenceItems": [
                  {
                    "parameter": 100,
                    "type": 4
                  }
                ],
                "customExpressionMode": false
              },
              "metaData": {}
            },
            "cases": [],
            "bargeIn": "Enabled",
            "bargeInDuration": {
              "config": {
                "lit": {
                  "pos": 1,
                  "text": "P0D0H0M0S500F",
                  "type": "dur"
                }
              },
              "text": "P0D0H0M0S500F",
              "type": "dur",
              "uiMetaData": {
                "mode": 1
              },
              "metaData": {}
            }
          },
          "failureTransferAudio": {
            "defaultAudio": {
              "text": "",
              "type": "aud",
              "uiMetaData": {
                "sequenceItems": []
              }
            },
            "cases": [],
            "bargeIn": "Enabled",
            "bargeInDuration": {
              "config": {
                "lit": {
                  "pos": 1,
                  "text": "P0D0H0M0S500F",
                  "type": "dur"
                }
              },
              "text": "P0D0H0M0S500F",
              "type": "dur",
              "uiMetaData": {
                "mode": 1
              },
              "metaData": {}
            }
          }
        }
      ],
      "variables": []
    },
    {
      "defaultMenuChoice": "b318e031-5048-4fdc-b1a6-30bc33c28d5f",
      "trackingId": 10,
      "id": "92fab14f-7de5-4473-b6ab-c972dfa8096b",
      "name": "OzInboundMenu",
      "uiMetaData": {},
      "__type": "Menu",
      "extensionDialingDelay": {
        "config": {
          "emp": {
            "pos": 1,
            "text": "",
            "type": "dur"
          }
        },
        "text": "",
        "type": "dur",
        "uiMetaData": {
          "mode": 1
        },
        "metaData": {}
      },
      "invalidSpeechRecPromptsList": [],
      "menuChoiceList": [
        {
          "globalSpeech": false,
          "speechRecTerms": {
            "en-AU": []
          },
          "id": "b318e031-5048-4fdc-b1a6-30bc33c28d5f",
          "name": "Disconnect",
          "action": {
            "trackingId": 11,
            "id": "bf0ae71f-197e-405a-871e-139c2d615ab5",
            "name": "Disconnect",
            "__type": "DisconnectAction"
          },
          "digit": 9
        },
        {
          "globalSpeech": false,
          "speechRecTerms": {
            "en-AU": []
          },
          "id": "60c6f811-acb2-42d1-95f7-70ebf3209bcd",
          "name": "Get Salesforce Contact",
          "action": {
            "taskReference": "2c6645f4-eca3-4fe6-ac94-07c57c2877a7",
            "trackingId": 33,
            "id": "21d3f218-ed38-49ae-a056-eed32c17c845",
            "name": "Get Salesforce Contact",
            "__type": "TaskAction"
          },
          "digit": 1
        },
        {
          "globalSpeech": false,
          "speechRecTerms": {
            "en-AU": []
          },
          "id": "d278cf2c-998a-467b-9be6-3067f612a394",
          "name": "Get Script",
          "action": {
            "taskReference": "40bc01f7-b958-4b94-8967-1d2b43bbef4a",
            "trackingId": 84,
            "id": "ac64c9e0-1111-4780-996a-ee0d89181f29",
            "name": "Get Script",
            "__type": "TaskAction"
          },
          "digit": 2
        }
      ],
      "promptRepeatCount": {
        "config": {
          "lit": {
            "pos": 1,
            "text": "4",
            "type": "int"
          }
        },
        "text": "4",
        "type": "int",
        "uiMetaData": {
          "mode": 1,
          "isOverride": true
        },
        "metaData": {}
      },
      "promptRepeatDelay": {
        "config": {
          "lit": {
            "pos": 1,
            "text": "P0D0H0M10S0F",
            "type": "dur"
          }
        },
        "text": "P0D0H0M10S0F",
        "type": "dur",
        "uiMetaData": {
          "mode": 1,
          "isOverride": true
        },
        "metaData": {}
      },
      "prompts": {
        "defaultAudio": {
          "config": {
            "Append": {
              "pos": 1,
              "text": "Append(ToAudioBlank(100), ToAudioTTS(\"One for S F D C\"), ToAudioBlank(100), ToAudioTTS(\"Two for S C R I P T\"))",
              "operands": [
                {
                  "ToAudioBlank": {
                    "pos": 8,
                    "text": "ToAudioBlank(100)",
                    "operands": [
                      {
                        "lit": {
                          "pos": 21,
                          "text": "100",
                          "type": "int"
                        }
                      }
                    ],
                    "type": "aud"
                  }
                },
                {
                  "ToAudioTTS": {
                    "pos": 27,
                    "text": "ToAudioTTS(\"One for S F D C\")",
                    "operands": [
                      {
                        "lit": {
                          "pos": 38,
                          "text": "One for S F D C",
                          "type": "str"
                        }
                      }
                    ],
                    "type": "aud"
                  }
                },
                {
                  "ToAudioBlank": {
                    "pos": 58,
                    "text": "ToAudioBlank(100)",
                    "operands": [
                      {
                        "lit": {
                          "pos": 71,
                          "text": "100",
                          "type": "int"
                        }
                      }
                    ],
                    "type": "aud"
                  }
                },
                {
                  "ToAudioTTS": {
                    "pos": 77,
                    "text": "ToAudioTTS(\"Two for S C R I P T\")",
                    "operands": [
                      {
                        "lit": {
                          "pos": 88,
                          "text": "Two for S C R I P T",
                          "type": "str"
                        }
                      }
                    ],
                    "type": "aud"
                  }
                }
              ],
              "type": "aud"
            }
          },
          "text": "Append(ToAudioBlank(100), ToAudioTTS(\"One for S F D C\"), ToAudioBlank(100), ToAudioTTS(\"Two for S C R I P T\"))",
          "type": "aud",
          "uiMetaData": {
            "sequenceItems": [
              {
                "parameter": 100,
                "type": 4
              },
              {
                "type": 0,
                "parameter": "One for S F D C"
              },
              {
                "parameter": 100,
                "type": 4
              },
              {
                "type": 0,
                "parameter": "Two for S C R I P T"
              }
            ],
            "customExpressionMode": false,
            "optional": true
          },
          "metaData": {}
        },
        "cases": [],
        "bargeIn": "Enabled",
        "bargeInDuration": {
          "config": {
            "lit": {
              "pos": 1,
              "text": "P0D0H0M0S500F",
              "type": "dur"
            }
          },
          "text": "P0D0H0M0S500F",
          "type": "dur",
          "uiMetaData": {
            "mode": 1
          },
          "metaData": {}
        }
      },
      "speechRecMinConfidence": {
        "config": {
          "emp": {
            "pos": 1,
            "text": "",
            "type": "int"
          }
        },
        "text": "",
        "type": "int",
        "uiMetaData": {
          "mode": 0
        },
        "metaData": {}
      },
      "speechRecTimeoutComplete": {
        "config": {
          "emp": {
            "pos": 1,
            "text": "",
            "type": "dur"
          }
        },
        "text": "",
        "type": "dur",
        "uiMetaData": {
          "mode": 0
        },
        "metaData": {}
      },
      "speechRecTimeoutIncomplete": {
        "config": {
          "emp": {
            "pos": 1,
            "text": "",
            "type": "dur"
          }
        },
        "text": "",
        "type": "dur",
        "uiMetaData": {
          "mode": 0
        },
        "metaData": {}
      },
      "speechRecTimeoutTotal": {
        "config": {
          "emp": {
            "pos": 1,
            "text": "",
            "type": "dur"
          }
        },
        "text": "",
        "type": "dur",
        "uiMetaData": {
          "mode": 0
        },
        "metaData": {}
      },
      "useExtensionDialing": {
        "config": {
          "emp": {
            "pos": 1,
            "text": "",
            "type": "bln"
          }
        },
        "text": "",
        "type": "bln",
        "uiMetaData": {
          "mode": 1
        },
        "metaData": {}
      }
    }
  ],
  "variables": [
    {
      "enableInitialValue": false,
      "id": "49fb79cb-3cac-4197-b130-20e1fb8fa7ef",
      "isCollection": false,
      "isInternal": false,
      "isOutput": false,
      "isInput": false,
      "isSecure": false,
      "name": "Flow.Fullname",
      "version": "1.0",
      "__type": "StringVariable",
      "initialValue": {
        "config": {
          "emp": {
            "pos": 1,
            "text": "",
            "type": "str"
          }
        },
        "text": "",
        "type": "str",
        "uiMetaData": {
          "mode": 1
        },
        "metaData": {}
      }
    }
  ]
}